skillport/__init__.py
skillport/__main__.py
skillport/interfaces/cli/__init__.py
skillport/interfaces/cli/app.py
skillport/interfaces/cli/catalog.py
skillport/interfaces/cli/config.py
skillport/interfaces/cli/context.py
skillport/interfaces/cli/theme.py
skillport/interfaces/cli/commands/add.py
skillport/interfaces/cli/commands/doc.py
skillport/interfaces/cli/commands/init.py
skillport/interfaces/cli/commands/list.py
skillport/interfaces/cli/commands/meta.py
skillport/interfaces/cli/commands/remove.py
skillport/interfaces/cli/commands/show.py
skillport/interfaces/cli/commands/update.py
skillport/interfaces/cli/commands/validate.py
skillport/interfaces/mcp/__init__.py
skillport/interfaces/mcp/cli.py
skillport/interfaces/mcp/instructions.py
skillport/interfaces/mcp/server.py
skillport/interfaces/mcp/tools.py
skillport/modules/__init__.py
skillport/modules/indexing/__init__.py
skillport/modules/indexing/internal/__init__.py
skillport/modules/indexing/internal/embeddings.py
skillport/modules/indexing/internal/lancedb.py
skillport/modules/indexing/internal/models.py
skillport/modules/indexing/internal/search_service.py
skillport/modules/indexing/internal/state.py
skillport/modules/indexing/public/__init__.py
skillport/modules/indexing/public/index.py
skillport/modules/indexing/public/query.py
skillport/modules/indexing/public/types.py
skillport/modules/skills/__init__.py
skillport/modules/skills/internal/__init__.py
skillport/modules/skills/internal/github.py
skillport/modules/skills/internal/manager.py
skillport/modules/skills/internal/origin.py
skillport/modules/skills/internal/tracking.py
skillport/modules/skills/internal/validation.py
skillport/modules/skills/internal/zip_handler.py
skillport/modules/skills/public/__init__.py
skillport/modules/skills/public/add.py
skillport/modules/skills/public/list.py
skillport/modules/skills/public/load.py
skillport/modules/skills/public/read.py
skillport/modules/skills/public/remove.py
skillport/modules/skills/public/search.py
skillport_core-1.1.0.dist-info/METADATA
skillport_core-1.1.0.dist-info/WHEEL
skillport_core-1.1.0.dist-info/RECORD
