Metadata-Version: 2.4
Name: skillport-core
Version: 1.1.0
Summary: Core SkillPort library (shared logic). See https://github.com/gotalab/skillport for documentation.
Project-URL: Homepage, https://github.com/gotalab/skillport
Project-URL: Repository, https://github.com/gotalab/skillport
Author: Gota
License-Expression: MIT
Keywords: agent-skills,context-engineering,mcp
Classifier: Development Status :: 4 - Beta
Classifier: License :: OSI Approved :: MIT License
Classifier: Programming Language :: Python :: 3
Classifier: Programming Language :: Python :: 3 :: Only
Classifier: Programming Language :: Python :: 3.10
Classifier: Programming Language :: Python :: 3.11
Classifier: Programming Language :: Python :: 3.12
Classifier: Programming Language :: Python :: 3.13
Classifier: Programming Language :: Python :: 3.14
Requires-Python: >=3.10
Requires-Dist: pydantic-settings>=2.0.0
Requires-Dist: pydantic>=2.0.0
Requires-Dist: pyyaml>=5.1
Requires-Dist: requests>=2.20.0
